dggstools/__init__.py
dggstools/__main__.py
dggstools/auids/__init__.py
dggstools/auids/common.py
dggstools/auids/rhpx.py
dggstools/rhpx/__init__.py
dggstools/rhpx/raster_to_rhpx.py
dggstools/rhpx/rhpx_gdf_helper.py
dggstools/rhpx/rhpxutils.py
dggstools/rhpx/vector_to_rhpx.py
dggstools/rhpx/utils/__init__.py
dggstools/rhpx/utils/rasterutils.py
dggstools/rhpx/utils/storage.py
dggstools/rhpx/utils/utils.py
dggstools/rhpx/utils/vectorutils.py
dggstools-0.1.2.dist-info/LICENSE
dggstools-0.1.2.dist-info/METADATA
dggstools-0.1.2.dist-info/WHEEL
dggstools-0.1.2.dist-info/entry_points.txt
dggstools-0.1.2.dist-info/top_level.txt
dggstools-0.1.2.dist-info/RECORD
