Metadata-Version: 2.1
Name: dggstools
Version: 0.1.2
Summary: A Python library and command line tool to manipulate raster and vector GIS data in a DGGS (rHEALPix for now).
Author-email: Rubén Béjar <rbejar@unizar.es>, Sergio Martin-Segura <segura@unizar.es>, "Francisco J. Lopez-Pellicer" <fjlopez@unizar.es>, Javier Nogueras-Iso <jnog@unizar.es>, "F. Javier Zarazaga-Soria" <javy@unizar.es>
Project-URL: Homepage, https://github.com/IAAA-Lab/dggstools
Project-URL: Issues, https://github.com/IAAA-Lab/dggstools/issues
Project-URL: Changelog, https://github.com/IAAA-Lab/dggstools/blob/main/changelog.md
Classifier: Programming Language :: Python :: 3
Classifier: License :: OSI Approved :: GNU Affero General Public License v3
Classifier: Operating System :: OS Independent
Classifier: Development Status :: 4 - Beta
Classifier: Topic :: Scientific/Engineering
Requires-Python: >=3.10
License-File: LICENSE
Requires-Dist: affine==2.3.1
Requires-Dist: attrs==21.4.0
Requires-Dist: boto3==1.35.60
Requires-Dist: botocore==1.35.60
Requires-Dist: build==1.0.3
Requires-Dist: certifi==2024.8.30
Requires-Dist: click==8.1.2
Requires-Dist: click-plugins==1.1.1
Requires-Dist: cligj==0.7.2
Requires-Dist: cycler==0.11.0
Requires-Dist: fiona==1.10.1
Requires-Dist: fonttools==4.48.1
Requires-Dist: GeoAlchemy2==0.12.5
Requires-Dist: geopandas==0.14.0
Requires-Dist: jmespath==1.0.0
Requires-Dist: kiwisolver==1.4.7
Requires-Dist: matplotlib==3.8.4
Requires-Dist: munch==2.5.0
Requires-Dist: networkx==2.8.7
Requires-Dist: numpy==1.26.4
Requires-Dist: packaging==24.0
Requires-Dist: pandas==2.2.2
Requires-Dist: pillow==10.4.0
Requires-Dist: psycopg2-binary==2.9.9
Requires-Dist: pyarrow==15.0.0
Requires-Dist: pyogrio==0.7.2
Requires-Dist: pyparsing==3.0.7
Requires-Dist: pyproj==3.6.1
Requires-Dist: python-dateutil==2.8.2
Requires-Dist: pytz==2022.1
Requires-Dist: rasterio==1.3.9
Requires-Dist: rHEALPixDGGS==0.5.4
Requires-Dist: s3transfer==0.10.0
Requires-Dist: scipy==1.12.0
Requires-Dist: shapely==2.0.4
Requires-Dist: six==1.16.0
Requires-Dist: snuggs==1.4.7
Requires-Dist: SQLAlchemy==2.0.21
Requires-Dist: SQLAlchemy-Utils==0.41.1
Requires-Dist: typer[all]==0.9.0
Requires-Dist: urllib3==2.2.3
